technobits/__init__.py
technobits/settings.py
technobits/urls.py
technobits/auth/__init__.py
technobits/auth/admin.py
technobits/auth/apps.py
technobits/auth/models.py
technobits/auth/serializers.py
technobits/auth/services.py
technobits/auth/urls.py
technobits/auth/utils.py
technobits/auth/views.py
technobits/auth/migrations/0001_initial.py
technobits/auth/migrations/__init__.py
technobits/email/__init__.py
technobits/email/apps.py
technobits/email/services.py
technobits/email/urls.py
technobits_server_django-1.0.0.dist-info/METADATA
technobits_server_django-1.0.0.dist-info/WHEEL
technobits_server_django-1.0.0.dist-info/top_level.txt
technobits_server_django-1.0.0.dist-info/RECORD
