Metadata-Version: 2.4
Name: technobits-server-django
Version: 1.0.0
Summary: Technobits Server Django Package - Modular auth, payments, and utilities for Django
Home-page: https://github.com/technobits/technobits-library
Author: Technobits
Author-email: Technobits <dev@technobits.com>
License: MIT
Project-URL: Homepage, https://github.com/technobits/technobits-library
Project-URL: Documentation, https://github.com/technobits/technobits-library/docs
Project-URL: Repository, https://github.com/technobits/technobits-library
Project-URL: Issues, https://github.com/technobits/technobits-library/issues
Classifier: Development Status :: 5 - Production/Stable
Classifier: Intended Audience :: Developers
Classifier: License :: OSI Approved :: MIT License
Classifier: Operating System :: OS Independent
Classifier: Programming Language :: Python :: 3
Classifier: Programming Language :: Python :: 3.8
Classifier: Programming Language :: Python :: 3.9
Classifier: Programming Language :: Python :: 3.10
Classifier: Programming Language :: Python :: 3.11
Classifier: Programming Language :: Python :: 3.12
Classifier: Framework :: Django
Classifier: Framework :: Django :: 4.0
Classifier: Framework :: Django :: 4.1
Classifier: Framework :: Django :: 4.2
Classifier: Framework :: Django :: 5.0
Requires-Python: >=3.8
Requires-Dist: Django<6.0,>=4.0
Requires-Dist: djangorestframework>=3.14.0
Requires-Dist: djangorestframework-simplejwt>=5.3.0
Requires-Dist: django-cors-headers>=4.3.0
Requires-Dist: google-auth>=2.23.0
Requires-Dist: requests>=2.31.0
Requires-Dist: sib-api-v3-sdk>=7.6.0
Requires-Dist: python-dotenv>=1.0.0
Provides-Extra: dev
Requires-Dist: pytest>=7.0; extra == "dev"
Requires-Dist: pytest-django>=4.5; extra == "dev"
Requires-Dist: black>=23.0; extra == "dev"
Requires-Dist: flake8>=6.0; extra == "dev"
Requires-Dist: mypy>=1.0; extra == "dev"
Provides-Extra: redis
Requires-Dist: redis>=4.0; extra == "redis"
Provides-Extra: postgres
Requires-Dist: psycopg2-binary>=2.9; extra == "postgres"
Provides-Extra: stripe
Requires-Dist: stripe>=5.0; extra == "stripe"
Dynamic: author
Dynamic: home-page
Dynamic: requires-python
